deepforest_modal_app/__init__.py
deepforest_modal_app/settings.py
deepforest_modal_app-0.1.0.dist-info/licenses/LICENSE
deepforest_modal_app-0.1.0.dist-info/METADATA
deepforest_modal_app-0.1.0.dist-info/WHEEL
deepforest_modal_app-0.1.0.dist-info/top_level.txt
deepforest_modal_app-0.1.0.dist-info/RECORD
