Metadata-Version: 2.4
Name: deepforest-modal-app
Version: 0.1.0
Summary: Modal app for training and inference of DeepForest models
Author-email: Martí Bosch <marti.bosch@epfl.ch>
License: GPL-3.0
Project-URL: Repository, https://github.com/martibosch/deepforest-modal-app
Classifier: License :: OSI Approved :: GNU General Public License v3 (GPLv3)
Classifier: Natural Language :: English
Classifier: Programming Language :: Python :: 3
Classifier: Programming Language :: Python :: 3.10
Classifier: Programming Language :: Python :: 3.11
Classifier: Programming Language :: Python :: 3.12
Classifier: Programming Language :: Python :: 3.13
Requires-Python: >=3.10
License-File: LICENSE
Requires-Dist: modal
Requires-Dist: geopandas>=1.0.0
Requires-Dist: rasterio>=1.0.0
Provides-Extra: dev
Requires-Dist: build; extra == "dev"
Requires-Dist: commitizen; extra == "dev"
Requires-Dist: pip; extra == "dev"
Requires-Dist: pre-commit; extra == "dev"
Requires-Dist: toml; extra == "dev"
Requires-Dist: tox; extra == "dev"
Requires-Dist: twine; extra == "dev"
Provides-Extra: doc
Requires-Dist: myst-parser; extra == "doc"
Requires-Dist: nbsphinx; extra == "doc"
Requires-Dist: pydata-sphinx-theme; extra == "doc"
Requires-Dist: sphinx; extra == "doc"
Requires-Dist: sphinxemoji; extra == "doc"
Provides-Extra: test
Requires-Dist: coverage[toml]; extra == "test"
Requires-Dist: pytest; extra == "test"
Requires-Dist: pytest-cov; extra == "test"
Requires-Dist: ruff; extra == "test"
Dynamic: license-file
